[{"start": 2.12, "end": 7.31, "text": "I wore makeup when we dated'cause I thought you'd like me more", "language": "english", "words": [{"word": "I", "start": 2.12, "end": 2.23, "score": 0.96, "syllables": [{"syllable": "I", "start": 2.12, "end": 2.23}]}, {"word": "wore", "start": 2.23, "end": 2.44, "score": 0.97, "syllables": [{"syllable": "wore", "start": 2.23, "end": 2.44}]}, {"word": "makeup", "start": 2.58, "end": 3.31, "score": 0.82, "syllables": [{"syllable": "makeup", "start": 2.58, "end": 3.31}]}, {"word": "when", "start": 3.45, "end": 3.66, "score": 0.98, "syllables": [{"syllable": "when", "start": 3.45, "end": 3.66}]}, {"word": "we", "start": 3.73, "end": 3.8, "score": 0.99, "syllables": [{"syllable": "we", "start": 3.73, "end": 3.8}]}, {"word": "dated'cause", "start": 4.01, "end": 5.05, "score": 0.97, "syllables": [{"syllable": "dated'", "start": 4.01, "end": 4.63}, {"syllable": "cause", "start": 4.63, "end": 5.05}]}, {"word": "I", "start": 5.05, "end": 5.15, "score": 0.98, "syllables": [{"syllable": "I", "start": 5.05, "end": 5.15}]}, {"word": "thought", "start": 5.5, "end": 5.78, "score": 0.91, "syllables": [{"syllable": "thought", "start": 5.5, "end": 5.78}]}, {"word": "you'd", "start": 5.89, "end": 6.03, "score": 0.98, "syllables": [{"syllable": "you'd", "start": 5.89, "end": 6.03}]}, {"word": "like", "start": 6.06, "end": 6.27, "score": 0.98, "syllables": [{"syllable": "like", "start": 6.06, "end": 6.27}]}, {"word": "me", "start": 6.55, "end": 6.65, "score": 0.99, "syllables": [{"syllable": "me", "start": 6.55, "end": 6.65}]}, {"word": "more", "start": 6.76, "end": 7.31, "score": 0.98, "syllables": [{"syllable": "more", "start": 6.76, "end": 7.31}]}]}, {"start": 7.45, "end": 13.24, "text": "If I looked like the other prom queens I know that you loved before", "language": "english", "words": [{"word": "If", "start": 7.45, "end": 7.56, "score": 0.99, "syllables": [{"syllable": "If", "start": 7.45, "end": 7.56}]}, {"word": "I", "start": 7.59, "end": 7.7, "score": 0.99, "syllables": [{"syllable": "I", "start": 7.59, "end": 7.7}]}, {"word": "looked", "start": 7.84, "end": 8.05, "score": 0.8, "syllables": [{"syllable": "looked", "start": 7.84, "end": 8.05}]}, {"word": "like", "start": 8.15, "end": 8.5, "score": 0.98, "syllables": [{"syllable": "like", "start": 8.15, "end": 8.5}]}, {"word": "the", "start": 8.57, "end": 8.78, "score": 0.97, "syllables": [{"syllable": "the", "start": 8.57, "end": 8.78}]}, {"word": "other", "start": 8.85, "end": 9.51, "score": 0.97, "syllables": [{"syllable": "oth", "start": 8.85, "end": 9.09}, {"syllable": "er", "start": 9.09, "end": 9.51}]}, {"word": "prom", "start": 9.51, "end": 9.89, "score": 0.92, "syllables": [{"syllable": "prom", "start": 9.51, "end": 9.89}]}, {"word": "queens", "start": 10.07, "end": 10.41, "score": 0.97, "syllables": [{"syllable": "queens", "start": 10.07, "end": 10.41}]}, {"word": "I", "start": 10.48, "end": 10.55, "score": 0.91, "syllables": [{"syllable": "I", "start": 10.48, "end": 10.55}]}, {"word": "know", "start": 10.66, "end": 10.76, "score": 0.87, "syllables": [{"syllable": "know", "start": 10.66, "end": 10.76}]}, {"word": "that", "start": 11.04, "end": 11.32, "score": 0.95, "syllables": [{"syllable": "that", "start": 11.04, "end": 11.32}]}, {"word": "you", "start": 11.46, "end": 11.56, "score": 0.99, "syllables": [{"syllable": "you", "start": 11.46, "end": 11.56}]}, {"word": "loved", "start": 11.63, "end": 12.09, "score": 0.96, "syllables": [{"syllable": "loved", "start": 11.63, "end": 12.09}]}, {"word": "before", "start": 12.16, "end": 13.24, "score": 0.96, "syllables": [{"syllable": "be", "start": 12.16, "end": 12.23}, {"syllable": "fore", "start": 12.23, "end": 13.24}]}]}, {"start": 13.24, "end": 17.87, "text": "Tried so hard to be everything that you liked", "language": "english", "words": [{"word": "Tried", "start": 13.24, "end": 13.55, "score": 0.89, "syllables": [{"syllable": "Tried", "start": 13.24, "end": 13.55}]}, {"word": "so", "start": 13.65, "end": 13.79, "score": 0.98, "syllables": [{"syllable": "so", "start": 13.65, "end": 13.79}]}, {"word": "hard", "start": 13.97, "end": 14.28, "score": 0.97, "syllables": [{"syllable": "hard", "start": 13.97, "end": 14.28}]}, {"word": "to", "start": 14.35, "end": 14.45, "score": 0.99, "syllables": [{"syllable": "to", "start": 14.35, "end": 14.45}]}, {"word": "be", "start": 14.49, "end": 14.63, "score": 0.99, "syllables": [{"syllable": "be", "start": 14.49, "end": 14.63}]}, {"word": "everything", "start": 14.87, "end": 15.74, "score": 0.97, "syllables": [{"syllable": "everything", "start": 14.87, "end": 15.74}]}, {"word": "that", "start": 16.09, "end": 16.3, "score": 0.96, "syllables": [{"syllable": "that", "start": 16.09, "end": 16.3}]}, {"word": "you", "start": 16.44, "end": 16.58, "score": 0.99, "syllables": [{"syllable": "you", "start": 16.44, "end": 16.58}]}, {"word": "liked", "start": 16.68, "end": 17.87, "score": 0.88, "syllables": [{"syllable": "liked", "start": 16.68, "end": 17.87}]}]}, {"start": 17.94, "end": 22.95, "text": "Just for you to say you're not the compliment type", "language": "english", "words": [{"word": "Just", "start": 17.94, "end": 18.22, "score": 0.97, "syllables": [{"syllable": "Just", "start": 17.94, "end": 18.22}]}, {"word": "for", "start": 18.63, "end": 18.81, "score": 0.96, "syllables": [{"syllable": "for", "start": 18.63, "end": 18.81}]}, {"word": "you", "start": 19.02, "end": 19.12, "score": 0.99, "syllables": [{"syllable": "you", "start": 19.02, "end": 19.12}]}, {"word": "to", "start": 19.3, "end": 19.4, "score": 0.99, "syllables": [{"syllable": "to", "start": 19.3, "end": 19.4}]}, {"word": "say", "start": 19.54, "end": 19.96, "score": 0.98, "syllables": [{"syllable": "say", "start": 19.54, "end": 19.96}]}, {"word": "you're", "start": 19.99, "end": 20.13, "score": 0.92, "syllables": [{"syllable": "you're", "start": 19.99, "end": 20.13}]}, {"word": "not", "start": 20.2, "end": 20.45, "score": 0.98, "syllables": [{"syllable": "not", "start": 20.2, "end": 20.45}]}, {"word": "the", "start": 20.55, "end": 20.65, "score": 0.95, "syllables": [{"syllable": "the", "start": 20.55, "end": 20.65}]}, {"word": "compliment", "start": 21.07, "end": 22.74, "score": 0.88, "syllables": [{"syllable": "com", "start": 21.07, "end": 21.32}, {"syllable": "pli", "start": 21.32, "end": 22.26}, {"syllable": "ment", "start": 22.26, "end": 22.74}]}, {"word": "type", "start": 22.74, "end": 22.95, "score": 0.99, "syllables": [{"syllable": "type", "start": 22.74, "end": 22.95}]}]}, {"start": 24.76, "end": 30.35, "text": "And I knew how you took your coffee and your favorite songs by heart", "language": "english", "words": [{"word": "And", "start": 24.76, "end": 24.9, "score": 0.95, "syllables": [{"syllable": "And", "start": 24.76, "end": 24.9}]}, {"word": "I", "start": 24.94, "end": 25.04, "score": 0.99, "syllables": [{"syllable": "I", "start": 24.94, "end": 25.04}]}, {"word": "knew", "start": 25.18, "end": 25.25, "score": 0.94, "syllables": [{"syllable": "knew", "start": 25.18, "end": 25.25}]}, {"word": "how", "start": 25.5, "end": 25.63, "score": 0.98, "syllables": [{"syllable": "how", "start": 25.5, "end": 25.63}]}, {"word": "you", "start": 26.02, "end": 26.09, "score": 0.98, "syllables": [{"syllable": "you", "start": 26.02, "end": 26.09}]}, {"word": "took", "start": 26.23, "end": 26.4, "score": 0.97, "syllables": [{"syllable": "took", "start": 26.23, "end": 26.4}]}, {"word": "your", "start": 26.54, "end": 26.75, "score": 0.94, "syllables": [{"syllable": "your", "start": 26.54, "end": 26.75}]}, {"word": "coffee", "start": 26.89, "end": 27.93, "score": 0.96, "syllables": [{"syllable": "cof", "start": 26.89, "end": 27.31}, {"syllable": "fee", "start": 27.31, "end": 27.93}]}, {"word": "and", "start": 27.93, "end": 28.11, "score": 0.21, "syllables": [{"syllable": "and", "start": 27.93, "end": 28.11}]}, {"word": "your", "start": 28.14, "end": 28.25, "score": 0.94, "syllables": [{"syllable": "your", "start": 28.14, "end": 28.25}]}, {"word": "favorite", "start": 28.35, "end": 29.01, "score": 0.69, "syllables": [{"syllable": "fa", "start": 28.35, "end": 28.49}, {"syllable": "vor", "start": 28.49, "end": 28.8}, {"syllable": "ite", "start": 28.8, "end": 29.01}]}, {"word": "songs", "start": 29.01, "end": 29.47, "score": 0.94, "syllables": [{"syllable": "songs", "start": 29.01, "end": 29.47}]}, {"word": "by", "start": 29.5, "end": 29.64, "score": 0.99, "syllables": [{"syllable": "by", "start": 29.5, "end": 29.64}]}, {"word": "heart", "start": 29.85, "end": 30.35, "score": 0.99, "syllables": [{"syllable": "heart", "start": 29.85, "end": 30.35}]}]}, {"start": 30.48, "end": 35.71, "text": "I read all of your selfhelp books, so you'd think that I was smart", "language": "english", "words": [{"word": "I", "start": 30.48, "end": 30.58, "score": 0.44, "syllables": [{"syllable": "I", "start": 30.48, "end": 30.58}]}, {"word": "read", "start": 30.75, "end": 31.0, "score": 0.36, "syllables": [{"syllable": "read", "start": 30.75, "end": 31.0}]}, {"word": "all", "start": 31.03, "end": 31.21, "score": 0.98, "syllables": [{"syllable": "all", "start": 31.03, "end": 31.21}]}, {"word": "of", "start": 31.35, "end": 31.49, "score": 0.86, "syllables": [{"syllable": "of", "start": 31.35, "end": 31.49}]}, {"word": "your", "start": 31.56, "end": 31.9, "score": 0.94, "syllables": [{"syllable": "your", "start": 31.56, "end": 31.9}]}, {"word": "self-help", "start": 32.11, "end": 32.81, "score": 0.99, "syllables": [{"syllable": "self", "start": 32.11, "end": 32.32}, {"syllable": "help", "start": 32.32, "end": 32.81}]}, {"word": "books,", "start": 32.81, "end": 33.16, "score": 0.94, "syllables": [{"syllable": "book", "start": 32.81, "end": 32.95}, {"syllable": "s,", "start": 32.95, "end": 33.16}]}, {"word": "so", "start": 33.16, "end": 33.3, "score": 0.94, "syllables": [{"syllable": "so", "start": 33.16, "end": 33.3}]}, {"word": "you'd", "start": 33.47, "end": 33.65, "score": 0.58, "syllables": [{"syllable": "you'd", "start": 33.47, "end": 33.65}]}, {"word": "think", "start": 34.03, "end": 34.27, "score": 0.95, "syllables": [{"syllable": "think", "start": 34.03, "end": 34.27}]}, {"word": "that", "start": 34.38, "end": 34.55, "score": 0.93, "syllables": [{"syllable": "that", "start": 34.38, "end": 34.55}]}, {"word": "I", "start": 34.59, "end": 34.69, "score": 0.99, "syllables": [{"syllable": "I", "start": 34.59, "end": 34.69}]}, {"word": "was", "start": 34.93, "end": 35.07, "score": 0.98, "syllables": [{"syllable": "was", "start": 34.93, "end": 35.07}]}, {"word": "smart", "start": 35.21, "end": 35.71, "score": 0.99, "syllables": [{"syllable": "smart", "start": 35.21, "end": 35.71}]}]}, {"start": 35.81, "end": 40.07, "text": "Stupid, emotional, obsessive little me", "language": "english", "words": [{"word": "Stupid,", "start": 35.81, "end": 36.54, "score": 0.95, "syllables": [{"syllable": "Stu", "start": 35.81, "end": 35.94}, {"syllable": "pid,", "start": 35.94, "end": 36.54}]}, {"word": "emotional,", "start": 36.54, "end": 37.41, "score": 0.98, "syllables": [{"syllable": "emo", "start": 36.54, "end": 36.78}, {"syllable": "tion", "start": 36.78, "end": 37.3}, {"syllable": "al,", "start": 37.3, "end": 37.41}]}, {"word": "obsessive", "start": 37.41, "end": 39.18, "score": 0.94, "syllables": [{"syllable": "ob", "start": 37.41, "end": 37.89}, {"syllable": "sess", "start": 37.89, "end": 38.59}, {"syllable": "ive", "start": 38.59, "end": 39.18}]}, {"word": "little", "start": 39.18, "end": 39.5, "score": 0.71, "syllables": [{"syllable": "little", "start": 39.18, "end": 39.5}]}, {"word": "me", "start": 39.57, "end": 40.07, "score": 0.93, "syllables": [{"syllable": "me", "start": 39.57, "end": 40.07}]}]}, {"start": 41.38, "end": 45.99, "text": "I knew from the start this is exactly how you'd leave", "language": "english", "words": [{"word": "I", "start": 41.38, "end": 41.41, "score": 0.99, "syllables": [{"syllable": "I", "start": 41.38, "end": 41.41}]}, {"word": "knew", "start": 41.48, "end": 41.62, "score": 0.95, "syllables": [{"syllable": "knew", "start": 41.48, "end": 41.62}]}, {"word": "from", "start": 41.87, "end": 42.11, "score": 0.94, "syllables": [{"syllable": "from", "start": 41.87, "end": 42.11}]}, {"word": "the", "start": 42.14, "end": 42.21, "score": 0.98, "syllables": [{"syllable": "the", "start": 42.14, "end": 42.21}]}, {"word": "start", "start": 42.42, "end": 42.88, "score": 0.97, "syllables": [{"syllable": "start", "start": 42.42, "end": 42.88}]}, {"word": "this", "start": 42.95, "end": 43.08, "score": 0.84, "syllables": [{"syllable": "this", "start": 42.95, "end": 43.08}]}, {"word": "is", "start": 43.15, "end": 43.47, "score": 0.96, "syllables": [{"syllable": "is", "start": 43.15, "end": 43.47}]}, {"word": "exactly", "start": 43.5, "end": 44.55, "score": 0.94, "syllables": [{"syllable": "ex", "start": 43.5, "end": 43.82}, {"syllable": "actly", "start": 43.82, "end": 44.55}]}, {"word": "how", "start": 44.55, "end": 44.65, "score": 0.98, "syllables": [{"syllable": "how", "start": 44.55, "end": 44.65}]}, {"word": "you'd", "start": 44.9, "end": 45.42, "score": 0.98, "syllables": [{"syllable": "you'd", "start": 44.9, "end": 45.42}]}, {"word": "leave", "start": 45.49, "end": 45.99, "score": 0.95, "syllables": [{"syllable": "leave", "start": 45.49, "end": 45.99}]}]}, {"start": 46.53, "end": 52.85, "text": "You found someone more exciting the next second you were gone", "language": "english", "words": [{"word": "You", "start": 46.53, "end": 46.64, "score": 0.99, "syllables": [{"syllable": "You", "start": 46.53, "end": 46.64}]}, {"word": "found", "start": 46.71, "end": 47.06, "score": 0.95, "syllables": [{"syllable": "found", "start": 46.71, "end": 47.06}]}, {"word": "someone", "start": 47.12, "end": 47.68, "score": 0.98, "syllables": [{"syllable": "someone", "start": 47.12, "end": 47.68}]}, {"word": "more", "start": 47.86, "end": 48.03, "score": 0.98, "syllables": [{"syllable": "more", "start": 47.86, "end": 48.03}]}, {"word": "exciting", "start": 48.34, "end": 49.42, "score": 0.97, "syllables": [{"syllable": "ex", "start": 48.34, "end": 48.55}, {"syllable": "cit", "start": 48.55, "end": 49.28}, {"syllable": "ing", "start": 49.28, "end": 49.42}]}, {"word": "the", "start": 49.42, "end": 49.49, "score": 0.94, "syllables": [{"syllable": "the", "start": 49.42, "end": 49.49}]}, {"word": "next", "start": 49.6, "end": 49.91, "score": 0.97, "syllables": [{"syllable": "next", "start": 49.6, "end": 49.91}]}, {"word": "second", "start": 49.95, "end": 50.43, "score": 0.98, "syllables": [{"syllable": "second", "start": 49.95, "end": 50.43}]}, {"word": "you", "start": 50.47, "end": 50.57, "score": 0.99, "syllables": [{"syllable": "you", "start": 50.47, "end": 50.57}]}, {"word": "were", "start": 51.17, "end": 51.55, "score": 0.98, "syllables": [{"syllable": "were", "start": 51.17, "end": 51.55}]}, {"word": "gone", "start": 52.35, "end": 52.85, "score": 0.98, "syllables": [{"syllable": "gone", "start": 52.35, "end": 52.85}]}]}, {"start": 52.56, "end": 57.38, "text": "And you left me there crying, wondering what I did wrong", "language": "english", "words": [{"word": "And", "start": 52.56, "end": 52.73, "score": 0.95, "syllables": [{"syllable": "And", "start": 52.56, "end": 52.73}]}, {"word": "you", "start": 52.77, "end": 52.91, "score": 0.99, "syllables": [{"syllable": "you", "start": 52.77, "end": 52.91}]}, {"word": "left", "start": 52.98, "end": 53.22, "score": 0.99, "syllables": [{"syllable": "left", "start": 52.98, "end": 53.22}]}, {"word": "me", "start": 53.32, "end": 53.46, "score": 0.98, "syllables": [{"syllable": "me", "start": 53.32, "end": 53.46}]}, {"word": "there", "start": 53.67, "end": 53.85, "score": 0.95, "syllables": [{"syllable": "there", "start": 53.67, "end": 53.85}]}, {"word": "crying,", "start": 53.99, "end": 54.75, "score": 0.69, "syllables": [{"syllable": "cry", "start": 53.99, "end": 54.13}, {"syllable": "ing,", "start": 54.13, "end": 54.75}]}, {"word": "wondering", "start": 54.75, "end": 55.66, "score": 0.94, "syllables": [{"syllable": "won", "start": 54.75, "end": 55.07}, {"syllable": "der", "start": 55.07, "end": 55.48}, {"syllable": "ing", "start": 55.48, "end": 55.66}]}, {"word": "what", "start": 55.66, "end": 55.97, "score": 0.97, "syllables": [{"syllable": "what", "start": 55.66, "end": 55.97}]}, {"word": "I", "start": 56.01, "end": 56.11, "score": 0.98, "syllables": [{"syllable": "I", "start": 56.01, "end": 56.11}]}, {"word": "did", "start": 56.29, "end": 56.81, "score": 0.98, "syllables": [{"syllable": "did", "start": 56.29, "end": 56.81}]}, {"word": "wrong", "start": 56.88, "end": 57.38, "score": 0.98, "syllables": [{"syllable": "wrong", "start": 56.88, "end": 57.38}]}]}, {"start": 57.23, "end": 60.13, "text": "And you always say I'm never", "language": "english", "words": [{"word": "And", "start": 57.23, "end": 57.4, "score": 0.96, "syllables": [{"syllable": "And", "start": 57.23, "end": 57.4}]}, {"word": "you", "start": 57.43, "end": 57.5, "score": 0.99, "syllables": [{"syllable": "you", "start": 57.43, "end": 57.5}]}, {"word": "always", "start": 57.57, "end": 58.44, "score": 0.97, "syllables": [{"syllable": "al", "start": 57.57, "end": 57.92}, {"syllable": "ways", "start": 57.92, "end": 58.44}]}, {"word": "say", "start": 58.44, "end": 58.65, "score": 0.98, "syllables": [{"syllable": "say", "start": 58.44, "end": 58.65}]}, {"word": "I'm", "start": 58.79, "end": 58.97, "score": 0.92, "syllables": [{"syllable": "I'm", "start": 58.79, "end": 58.97}]}, {"word": "never", "start": 59.18, "end": 60.13, "score": 0.99, "syllables": [{"syllable": "nev", "start": 59.18, "end": 59.49}, {"syllable": "er", "start": 59.49, "end": 60.13}]}]}]